{"value":"{\"created_at\":\"Wed Dec 09 08:17:23 +0000 2020\",\"id\":1336585723856773121,\"id_str\":\"1336585723856773121\",\"text\":\"RT @MzansiHotBaes: Portable iPhone \\ud83e\\udd75 https:\\/\\/t.co\\/tNjxZVXNDw\",\"source\":\"\\u003ca href=\\\"http:\\/\\/twitter.com\\/download\\/android\\\" rel=\\\"nofollow\\\"\\u003eTwitter for Android\\u003c\\/a\\u003e\",\"truncated\":false,\"in_reply_to_status_id\":null,\"in_reply_to_status_id_str\":null,\"in_reply_to_user_id\":null,\"in_reply_to_user_id_str\":null,\"in_reply_to_screen_name\":null,\"user\":{\"id\":1232270578603696129,\"id_str\":\"1232270578603696129\",\"name\":\"BabbyRixa\\ud83d\\udc51\\u2764\",\"screen_name\":\"BabyRixalandza\",\"location\":\"Vosloorus, South Africa\",\"url\":null,\"description\":\"My Crown May Tilt But It Will Never Fall\\ud83d\\udc51\",\"translator_type\":\"none\",\"protected\":false,\"verified\":false,\"followers_count\":5340,\"friends_count\":4034,\"listed_count\":0,\"favourites_count\":5142,\"statuses_count\":7016,\"created_at\":\"Tue Feb 25 11:46:47 +0000 2020\",\"utc_offset\":null,\"time_zone\":null,\"geo_enabled\":true,\"lang\":null,\"contributors_enabled\":false,\"is_translator\":false,\"profile_background_color\":\"F5F8FA\",\"profile_background_image_url\":\"\",\"profile_background_image_url_https\":\"\",\"profile_background_tile\":false,\"profile_link_color\":\"1DA1F2\",\"profile_sidebar_border_color\":\"C0DEED\",\"profile_sidebar_fill_color\":\"DDEEF6\",\"profile_text_color\":\"333333\",\"profile_use_background_image\":true,\"profile_image_url\":\"http:\\/\\/pbs.twimg.com\\/profile_images\\/1327961213456805889\\/PEiVMVSK_normal.jpg\",\"profile_image_url_https\":\"https:\\/\\/pbs.twimg.com\\/profile_images\\/1327961213456805889\\/PEiVMVSK_normal.jpg\",\"profile_banner_url\":\"https:\\/\\/pbs.twimg.com\\/profile_banners\\/1232270578603696129\\/1600768165\",\"default_profile\":true,\"default_profile_image\":false,\"following\":null,\"follow_request_sent\":null,\"notifications\":null},\"geo\":null,\"coordinates\":null,\"place\":null,\"contributors\":null,\"retweeted_status\":{\"created_at\":\"Wed Dec 09 05:43:49 +0000 2020\",\"id\":1336547074884644866,\"id_str\":\"1336547074884644866\",\"text\":\"Portable iPhone \\ud83e\\udd75 https:\\/\\/t.co\\/tNjxZVXNDw\",\"display_text_range\":[0,17],\"source\":\"\\u003ca href=\\\"http:\\/\\/twitter.com\\/download\\/iphone\\\" rel=\\\"nofollow\\\"\\u003eTwitter for iPhone\\u003c\\/a\\u003e\",\"truncated\":false,\"in_reply_to_status_id\":null,\"in_reply_to_status_id_str\":null,\"in_reply_to_user_id\":null,\"in_reply_to_user_id_str\":null,\"in_reply_to_screen_name\":null,\"user\":{\"id\":324846919,\"id_str\":\"324846919\",\"name\":\"Mzansi Hot Chicks \\ud83c\\udf2c\\ufe0f\\uf8ff\",\"screen_name\":\"MzansiHotBaes\",\"location\":\"Cape Coral, FL\",\"url\":null,\"description\":\"The Beauty Of African Queens \\ud83d\\udc78\",\"translator_type\":\"none\",\"protected\":false,\"verified\":false,\"followers_count\":25056,\"friends_count\":414,\"listed_count\":15,\"favourites_count\":3166,\"statuses_count\":22601,\"created_at\":\"Mon Jun 27 09:32:31 +0000 2011\",\"utc_offset\":null,\"time_zone\":null,\"geo_enabled\":false,\"lang\":null,\"contributors_enabled\":false,\"is_translator\":false,\"profile_background_color\":\"C0DEED\",\"profile_background_image_url\":\"http:\\/\\/abs.twimg.com\\/images\\/themes\\/theme1\\/bg.png\",\"profile_background_image_url_https\":\"https:\\/\\/abs.twimg.com\\/images\\/themes\\/theme1\\/bg.png\",\"profile_background_tile\":false,\"profile_link_color\":\"1DA1F2\",\"profile_sidebar_border_color\":\"C0DEED\",\"profile_sidebar_fill_color\":\"DDEEF6\",\"profile_text_color\":\"333333\",\"profile_use_background_image\":true,\"profile_image_url\":\"http:\\/\\/pbs.twimg.com\\/profile_images\\/1301900241294295040\\/NR7PbTfq_normal.jpg\",\"profile_image_url_https\":\"https:\\/\\/pbs.twimg.com\\/profile_images\\/1301900241294295040\\/NR7PbTfq_normal.jpg\",\"profile_banner_url\":\"https:\\/\\/pbs.twimg.com\\/profile_banners\\/324846919\\/1595675814\",\"default_profile\":true,\"default_profile_image\":false,\"following\":null,\"follow_request_sent\":null,\"notifications\":null},\"geo\":null,\"coordinates\":null,\"place\":null,\"contributors\":null,\"is_quote_status\":false,\"quote_count\":0,\"reply_count\":2,\"retweet_count\":27,\"favorite_count\":120,\"entities\":{\"hashtags\":[],\"urls\":[],\"user_mentions\":[],\"symbols\":[],\"media\":[{\"id\":1336547067351736320,\"id_str\":\"1336547067351736320\",\"indices\":[18,41],\"media_url\":\"http:\\/\\/pbs.twimg.com\\/media\\/EoxeefcXIAAYqta.jpg\",\"media_url_https\":\"https:\\/\\/pbs.twimg.com\\/media\\/EoxeefcXIAAYqta.jpg\",\"url\":\"https:\\/\\/t.co\\/tNjxZVXNDw\",\"display_url\":\"pic.twitter.com\\/tNjxZVXNDw\",\"expanded_url\":\"https:\\/\\/twitter.com\\/MzansiHotBaes\\/status\\/1336547074884644866\\/photo\\/1\",\"type\":\"photo\",\"sizes\":{\"large\":{\"w\":1242,\"h\":1473,\"resize\":\"fit\"},\"thumb\":{\"w\":150,\"h\":150,\"resize\":\"crop\"},\"medium\":{\"w\":1012,\"h\":1200,\"resize\":\"fit\"},\"small\":{\"w\":573,\"h\":680,\"resize\":\"fit\"}}}]},\"extended_entities\":{\"media\":[{\"id\":1336547067351736320,\"id_str\":\"1336547067351736320\",\"indices\":[18,41],\"media_url\":\"http:\\/\\/pbs.twimg.com\\/media\\/EoxeefcXIAAYqta.jpg\",\"media_url_https\":\"https:\\/\\/pbs.twimg.com\\/media\\/EoxeefcXIAAYqta.jpg\",\"url\":\"https:\\/\\/t.co\\/tNjxZVXNDw\",\"display_url\":\"pic.twitter.com\\/tNjxZVXNDw\",\"expanded_url\":\"https:\\/\\/twitter.com\\/MzansiHotBaes\\/status\\/1336547074884644866\\/photo\\/1\",\"type\":\"photo\",\"sizes\":{\"large\":{\"w\":1242,\"h\":1473,\"resize\":\"fit\"},\"thumb\":{\"w\":150,\"h\":150,\"resize\":\"crop\"},\"medium\":{\"w\":1012,\"h\":1200,\"resize\":\"fit\"},\"small\":{\"w\":573,\"h\":680,\"resize\":\"fit\"}}}]},\"favorited\":false,\"retweeted\":false,\"possibly_sensitive\":false,\"filter_level\":\"low\",\"lang\":\"en\"},\"is_quote_status\":false,\"quote_count\":0,\"reply_count\":0,\"retweet_count\":0,\"favorite_count\":0,\"entities\":{\"hashtags\":[],\"urls\":[],\"user_mentions\":[{\"screen_name\":\"MzansiHotBaes\",\"name\":\"Mzansi Hot Chicks \\ud83c\\udf2c\\ufe0f\\uf8ff\",\"id\":324846919,\"id_str\":\"324846919\",\"indices\":[3,17]}],\"symbols\":[],\"media\":[{\"id\":1336547067351736320,\"id_str\":\"1336547067351736320\",\"indices\":[37,60],\"media_url\":\"http:\\/\\/pbs.twimg.com\\/media\\/EoxeefcXIAAYqta.jpg\",\"media_url_https\":\"https:\\/\\/pbs.twimg.com\\/media\\/EoxeefcXIAAYqta.jpg\",\"url\":\"https:\\/\\/t.co\\/tNjxZVXNDw\",\"display_url\":\"pic.twitter.com\\/tNjxZVXNDw\",\"expanded_url\":\"https:\\/\\/twitter.com\\/MzansiHotBaes\\/status\\/1336547074884644866\\/photo\\/1\",\"type\":\"photo\",\"sizes\":{\"large\":{\"w\":1242,\"h\":1473,\"resize\":\"fit\"},\"thumb\":{\"w\":150,\"h\":150,\"resize\":\"crop\"},\"medium\":{\"w\":1012,\"h\":1200,\"resize\":\"fit\"},\"small\":{\"w\":573,\"h\":680,\"resize\":\"fit\"}},\"source_status_id\":1336547074884644866,\"source_status_id_str\":\"1336547074884644866\",\"source_user_id\":324846919,\"source_user_id_str\":\"324846919\"}]},\"extended_entities\":{\"media\":[{\"id\":1336547067351736320,\"id_str\":\"1336547067351736320\",\"indices\":[37,60],\"media_url\":\"http:\\/\\/pbs.twimg.com\\/media\\/EoxeefcXIAAYqta.jpg\",\"media_url_https\":\"https:\\/\\/pbs.twimg.com\\/media\\/EoxeefcXIAAYqta.jpg\",\"url\":\"https:\\/\\/t.co\\/tNjxZVXNDw\",\"display_url\":\"pic.twitter.com\\/tNjxZVXNDw\",\"expanded_url\":\"https:\\/\\/twitter.com\\/MzansiHotBaes\\/status\\/1336547074884644866\\/photo\\/1\",\"type\":\"photo\",\"sizes\":{\"large\":{\"w\":1242,\"h\":1473,\"resize\":\"fit\"},\"thumb\":{\"w\":150,\"h\":150,\"resize\":\"crop\"},\"medium\":{\"w\":1012,\"h\":1200,\"resize\":\"fit\"},\"small\":{\"w\":573,\"h\":680,\"resize\":\"fit\"}},\"source_status_id\":1336547074884644866,\"source_status_id_str\":\"1336547074884644866\",\"source_user_id\":324846919,\"source_user_id_str\":\"324846919\"}]},\"favorited\":false,\"retweeted\":false,\"possibly_sensitive\":false,\"filter_level\":\"low\",\"lang\":\"en\",\"timestamp_ms\":\"1607501843786\"}\r\n","test_col":1}
{"value":"{\"created_at\":\"Wed Dec 09 08:17:23 +0000 2020\",\"id\":1336585724015984641,\"id_str\":\"1336585724015984641\",\"text\":\"20000M Power Bank 10000mAh Portable Charger,T-CORE Smallest External Battery Lightest Ultra Compact High Speed 2USB\\u2026 https:\\/\\/t.co\\/NdW0Afnpan\",\"display_text_range\":[0,140],\"source\":\"\\u003ca href=\\\"https:\\/\\/mobile.twitter.com\\\" rel=\\\"nofollow\\\"\\u003eTwitter Web App\\u003c\\/a\\u003e\",\"truncated\":true,\"in_reply_to_status_id\":null,\"in_reply_to_status_id_str\":null,\"in_reply_to_user_id\":null,\"in_reply_to_user_id_str\":null,\"in_reply_to_screen_name\":null,\"user\":{\"id\":1268564862973538306,\"id_str\":\"1268564862973538306\",\"name\":\"Ellen Walker\",\"screen_name\":\"ellenwalker76\",\"location\":null,\"url\":null,\"description\":null,\"translator_type\":\"none\",\"protected\":false,\"verified\":false,\"followers_count\":3,\"friends_count\":0,\"listed_count\":0,\"favourites_count\":0,\"statuses_count\":18756,\"created_at\":\"Thu Jun 04 15:26:55 +0000 2020\",\"utc_offset\":null,\"time_zone\":null,\"geo_enabled\":false,\"lang\":null,\"contributors_enabled\":false,\"is_translator\":false,\"profile_background_color\":\"F5F8FA\",\"profile_background_image_url\":\"\",\"profile_background_image_url_https\":\"\",\"profile_background_tile\":false,\"profile_link_color\":\"1DA1F2\",\"profile_sidebar_border_color\":\"C0DEED\",\"profile_sidebar_fill_color\":\"DDEEF6\",\"profile_text_color\":\"333333\",\"profile_use_background_image\":true,\"profile_image_url\":\"http:\\/\\/pbs.twimg.com\\/profile_images\\/1268565306231816192\\/jlorXdOl_normal.png\",\"profile_image_url_https\":\"https:\\/\\/pbs.twimg.com\\/profile_images\\/1268565306231816192\\/jlorXdOl_normal.png\",\"default_profile\":true,\"default_profile_image\":false,\"following\":null,\"follow_request_sent\":null,\"notifications\":null},\"geo\":null,\"coordinates\":null,\"place\":null,\"contributors\":null,\"is_quote_status\":false,\"extended_tweet\":{\"full_text\":\"20000M Power Bank 10000mAh Portable Charger,T-CORE Smallest External Battery Lightest Ultra Compact High Speed 2USB Cell Phone Mobile Pack for iPhone Xs 8 7 6 Samsung Galaxy Note S9 iPad Tablet-Black https:\\/\\/t.co\\/yIZ9d9rHpo https:\\/\\/t.co\\/SMKNwVFvsY\",\"display_text_range\":[0,223],\"entities\":{\"hashtags\":[],\"urls\":[{\"url\":\"https:\\/\\/t.co\\/yIZ9d9rHpo\",\"expanded_url\":\"https:\\/\\/www.amazon.com\\/dp\\/B082ZVBTG6?tag=hmstwt-20\",\"display_url\":\"amazon.com\\/dp\\/B082ZVBTG6?\\u2026\",\"indices\":[200,223]}],\"user_mentions\":[],\"symbols\":[],\"media\":[{\"id\":1336585719591006208,\"id_str\":\"1336585719591006208\",\"indices\":[224,247],\"media_url\":\"http:\\/\\/pbs.twimg.com\\/media\\/EoyBoWQU8AAXyVb.png\",\"media_url_https\":\"https:\\/\\/pbs.twimg.com\\/media\\/EoyBoWQU8AAXyVb.png\",\"url\":\"https:\\/\\/t.co\\/SMKNwVFvsY\",\"display_url\":\"pic.twitter.com\\/SMKNwVFvsY\",\"expanded_url\":\"https:\\/\\/twitter.com\\/ellenwalker76\\/status\\/1336585724015984641\\/photo\\/1\",\"type\":\"photo\",\"sizes\":{\"large\":{\"w\":748,\"h\":834,\"resize\":\"fit\"},\"medium\":{\"w\":748,\"h\":834,\"resize\":\"fit\"},\"thumb\":{\"w\":150,\"h\":150,\"resize\":\"crop\"},\"small\":{\"w\":610,\"h\":680,\"resize\":\"fit\"}}}]},\"extended_entities\":{\"media\":[{\"id\":1336585719591006208,\"id_str\":\"1336585719591006208\",\"indices\":[224,247],\"media_url\":\"http:\\/\\/pbs.twimg.com\\/media\\/EoyBoWQU8AAXyVb.png\",\"media_url_https\":\"https:\\/\\/pbs.twimg.com\\/media\\/EoyBoWQU8AAXyVb.png\",\"url\":\"https:\\/\\/t.co\\/SMKNwVFvsY\",\"display_url\":\"pic.twitter.com\\/SMKNwVFvsY\",\"expanded_url\":\"https:\\/\\/twitter.com\\/ellenwalker76\\/status\\/1336585724015984641\\/photo\\/1\",\"type\":\"photo\",\"sizes\":{\"large\":{\"w\":748,\"h\":834,\"resize\":\"fit\"},\"medium\":{\"w\":748,\"h\":834,\"resize\":\"fit\"},\"thumb\":{\"w\":150,\"h\":150,\"resize\":\"crop\"},\"small\":{\"w\":610,\"h\":680,\"resize\":\"fit\"}}}]}},\"quote_count\":0,\"reply_count\":0,\"retweet_count\":0,\"favorite_count\":0,\"entities\":{\"hashtags\":[],\"urls\":[{\"url\":\"https:\\/\\/t.co\\/NdW0Afnpan\",\"expanded_url\":\"https:\\/\\/twitter.com\\/i\\/web\\/status\\/1336585724015984641\",\"display_url\":\"twitter.com\\/i\\/web\\/status\\/1\\u2026\",\"indices\":[117,140]}],\"user_mentions\":[],\"symbols\":[]},\"favorited\":false,\"retweeted\":false,\"possibly_sensitive\":false,\"filter_level\":\"low\",\"lang\":\"en\",\"timestamp_ms\":\"1607501843824\"}\r\n","test_col":1}
{"value":"{\"created_at\":\"Wed Dec 09 08:17:25 +0000 2020\",\"id\":1336585730512941057,\"id_str\":\"1336585730512941057\",\"text\":\"RT @spin9: \\u0e2a\\u0e34\\u0e48\\u0e07\\u0e17\\u0e35\\u0e48 Apple \\u0e40\\u0e1b\\u0e34\\u0e14\\u0e15\\u0e31\\u0e27\\u0e43\\u0e19\\u0e1b\\u0e35\\u0e19\\u0e35\\u0e49\\n\\n\\ud83d\\udcf1 iPad Pro 11\\u201d, 12.9\\u201d\\n\\u2328\\ufe0f Magic Keyboard for iPad\\n\\ud83d\\udcbb MacBook Air \\/ Pro (Intel)\\n\\ud83d\\udcf1 iPhone SE\\n\\ud83d\\udda5 iMac 27\\u2026\",\"source\":\"\\u003ca href=\\\"https:\\/\\/mobile.twitter.com\\\" rel=\\\"nofollow\\\"\\u003eTwitter Web App\\u003c\\/a\\u003e\",\"truncated\":false,\"in_reply_to_status_id\":null,\"in_reply_to_status_id_str\":null,\"in_reply_to_user_id\":null,\"in_reply_to_user_id_str\":null,\"in_reply_to_screen_name\":null,\"user\":{\"id\":1083472326,\"id_str\":\"1083472326\",\"name\":\"MJ\\ud83e\\udd0d\",\"screen_name\":\"MyMinCare\",\"location\":\"Thailand\",\"url\":null,\"description\":\"\\ud83d\\ude2c\\ud83d\\ude2c\\ud83d\\ude2c\\ud83d\\ude2c\\ud83d\\ude2c\\ud83d\\ude2c\",\"translator_type\":\"none\",\"protected\":false,\"verified\":false,\"followers_count\":52,\"friends_count\":136,\"listed_count\":1,\"favourites_count\":483,\"statuses_count\":42732,\"created_at\":\"Sat Jan 12 16:40:54 +0000 2013\",\"utc_offset\":null,\"time_zone\":null,\"geo_enabled\":true,\"lang\":null,\"contributors_enabled\":false,\"is_translator\":false,\"profile_background_color\":\"0099B9\",\"profile_background_image_url\":\"http:\\/\\/abs.twimg.com\\/images\\/themes\\/theme4\\/bg.gif\",\"profile_background_image_url_https\":\"https:\\/\\/abs.twimg.com\\/images\\/themes\\/theme4\\/bg.gif\",\"profile_background_tile\":true,\"profile_link_color\":\"0099B9\",\"profile_sidebar_border_color\":\"FFFFFF\",\"profile_sidebar_fill_color\":\"95E8EC\",\"profile_text_color\":\"3C3940\",\"profile_use_background_image\":true,\"profile_image_url\":\"http:\\/\\/pbs.twimg.com\\/profile_images\\/1184013769292169216\\/IDB1wy5b_normal.jpg\",\"profile_image_url_https\":\"https:\\/\\/pbs.twimg.com\\/profile_images\\/1184013769292169216\\/IDB1wy5b_normal.jpg\",\"profile_banner_url\":\"https:\\/\\/pbs.twimg.com\\/profile_banners\\/1083472326\\/1546941983\",\"default_profile\":false,\"default_profile_image\":false,\"following\":null,\"follow_request_sent\":null,\"notifications\":null},\"geo\":null,\"coordinates\":null,\"place\":null,\"contributors\":null,\"retweeted_status\":{\"created_at\":\"Wed Dec 09 02:00:50 +0000 2020\",\"id\":1336490962105733120,\"id_str\":\"1336490962105733120\",\"text\":\"\\u0e2a\\u0e34\\u0e48\\u0e07\\u0e17\\u0e35\\u0e48 Apple \\u0e40\\u0e1b\\u0e34\\u0e14\\u0e15\\u0e31\\u0e27\\u0e43\\u0e19\\u0e1b\\u0e35\\u0e19\\u0e35\\u0e49\\n\\n\\ud83d\\udcf1 iPad Pro 11\\u201d, 12.9\\u201d\\n\\u2328\\ufe0f Magic Keyboard for iPad\\n\\ud83d\\udcbb MacBook Air \\/ Pro (Intel)\\n\\ud83d\\udcf1 iPhone\\u2026 https:\\/\\/t.co\\/GoBwIXAhYN\",\"source\":\"\\u003ca href=\\\"http:\\/\\/twitter.com\\/download\\/iphone\\\" rel=\\\"nofollow\\\"\\u003eTwitter for iPhone\\u003c\\/a\\u003e\",\"truncated\":true,\"in_reply_to_status_id\":null,\"in_reply_to_status_id_str\":null,\"in_reply_to_user_id\":null,\"in_reply_to_user_id_str\":null,\"in_reply_to_screen_name\":null,\"user\":{\"id\":67251857,\"id_str\":\"67251857\",\"name\":\"spin9\",\"screen_name\":\"spin9\",\"location\":\"Bangkok, Thailand\",\"url\":\"http:\\/\\/www.youtube.com\\/spin9\",\"description\":\"\\u0e2d\\u0e39\\u0e4b spin9, Frequent flyer, Content creator.\",\"translator_type\":\"none\",\"protected\":false,\"verified\":false,\"followers_count\":154363,\"friends_count\":258,\"listed_count\":233,\"favourites_count\":115,\"statuses_count\":23943,\"created_at\":\"Thu Aug 20 06:58:36 +0000 2009\",\"utc_offset\":null,\"time_zone\":null,\"geo_enabled\":true,\"lang\":null,\"contributors_enabled\":false,\"is_translator\":false,\"profile_background_color\":\"C0DEED\",\"profile_background_image_url\":\"http:\\/\\/abs.twimg.com\\/images\\/themes\\/theme1\\/bg.png\",\"profile_background_image_url_https\":\"https:\\/\\/abs.twimg.com\\/images\\/themes\\/theme1\\/bg.png\",\"profile_background_tile\":true,\"profile_link_color\":\"444444\",\"profile_sidebar_border_color\":\"C0DEED\",\"profile_sidebar_fill_color\":\"DDEEF6\",\"profile_text_color\":\"333333\",\"profile_use_background_image\":true,\"profile_image_url\":\"http:\\/\\/pbs.twimg.com\\/profile_images\\/1213073892249604097\\/bc2db9jO_normal.jpg\",\"profile_image_url_https\":\"https:\\/\\/pbs.twimg.com\\/profile_images\\/1213073892249604097\\/bc2db9jO_normal.jpg\",\"profile_banner_url\":\"https:\\/\\/pbs.twimg.com\\/profile_banners\\/67251857\\/1510885677\",\"default_profile\":false,\"default_profile_image\":false,\"following\":null,\"follow_request_sent\":null,\"notifications\":null},\"geo\":null,\"coordinates\":null,\"place\":null,\"contributors\":null,\"is_quote_status\":false,\"extended_tweet\":{\"full_text\":\"\\u0e2a\\u0e34\\u0e48\\u0e07\\u0e17\\u0e35\\u0e48 Apple \\u0e40\\u0e1b\\u0e34\\u0e14\\u0e15\\u0e31\\u0e27\\u0e43\\u0e19\\u0e1b\\u0e35\\u0e19\\u0e35\\u0e49\\n\\n\\ud83d\\udcf1 iPad Pro 11\\u201d, 12.9\\u201d\\n\\u2328\\ufe0f Magic Keyboard for iPad\\n\\ud83d\\udcbb MacBook Air \\/ Pro (Intel)\\n\\ud83d\\udcf1 iPhone SE\\n\\ud83d\\udda5 iMac 27\\u201d\\n\\u231a\\ufe0f Apple Watch Series 6 \\/ SE\\n\\ud83d\\udcf1 iPad 8th\\n\\ud83d\\udcf1 iPad Air\\n\\ud83d\\udcf1 iPhone 12 (4 \\u0e23\\u0e38\\u0e48\\u0e19)\\n\\ud83d\\udd08 HomePod mini\\n\\ud83d\\udcbb MacBook Air \\/ Pro, Mac mini (M1)\\n\\ud83c\\udfa7 AirPods Max\",\"display_text_range\":[0,265],\"entities\":{\"hashtags\":[],\"urls\":[],\"user_mentions\":[],\"symbols\":[]}},\"quote_count\":53,\"reply_count\":2,\"retweet_count\":1667,\"favorite_count\":786,\"entities\":{\"hashtags\":[],\"urls\":[{\"url\":\"https:\\/\\/t.co\\/GoBwIXAhYN\",\"expanded_url\":\"https:\\/\\/twitter.com\\/i\\/web\\/status\\/1336490962105733120\",\"display_url\":\"twitter.com\\/i\\/web\\/status\\/1\\u2026\",\"indices\":[117,140]}],\"user_mentions\":[],\"symbols\":[]},\"favorited\":false,\"retweeted\":false,\"filter_level\":\"low\",\"lang\":\"en\"},\"is_quote_status\":false,\"quote_count\":0,\"reply_count\":0,\"retweet_count\":0,\"favorite_count\":0,\"entities\":{\"hashtags\":[],\"urls\":[],\"user_mentions\":[{\"screen_name\":\"spin9\",\"name\":\"spin9\",\"id\":67251857,\"id_str\":\"67251857\",\"indices\":[3,9]}],\"symbols\":[]},\"favorited\":false,\"retweeted\":false,\"filter_level\":\"low\",\"lang\":\"en\",\"timestamp_ms\":\"1607501845373\"}\r\n","test_col":1}
{"value":"{\"created_at\":\"Wed Dec 09 08:17:26 +0000 2020\",\"id\":1336585736758419459,\"id_str\":\"1336585736758419459\",\"text\":\"Do you love the scraps of food you get from an abusive partner? Then you love your partner and wouldn't leave them\\u2026 https:\\/\\/t.co\\/ckYD7t99zo\",\"source\":\"\\u003ca href=\\\"https:\\/\\/mobile.twitter.com\\\" rel=\\\"nofollow\\\"\\u003eTwitter Web App\\u003c\\/a\\u003e\",\"truncated\":true,\"in_reply_to_status_id\":null,\"in_reply_to_status_id_str\":null,\"in_reply_to_user_id\":null,\"in_reply_to_user_id_str\":null,\"in_reply_to_screen_name\":null,\"user\":{\"id\":1327710660478820356,\"id_str\":\"1327710660478820356\",\"name\":\"bigfiga\",\"screen_name\":\"bigfiga1\",\"location\":null,\"url\":null,\"description\":\"Hello, I am here to talk about anything that interests me from games, biology, art, movies, languages, philosophy and more :3\\nI'm Bi as well heh heh.\",\"translator_type\":\"none\",\"protected\":false,\"verified\":false,\"followers_count\":33,\"friends_count\":83,\"listed_count\":0,\"favourites_count\":323,\"statuses_count\":261,\"created_at\":\"Sat Nov 14 20:31:15 +0000 2020\",\"utc_offset\":null,\"time_zone\":null,\"geo_enabled\":false,\"lang\":null,\"contributors_enabled\":false,\"is_translator\":false,\"profile_background_color\":\"F5F8FA\",\"profile_background_image_url\":\"\",\"profile_background_image_url_https\":\"\",\"profile_background_tile\":false,\"profile_link_color\":\"1DA1F2\",\"profile_sidebar_border_color\":\"C0DEED\",\"profile_sidebar_fill_color\":\"DDEEF6\",\"profile_text_color\":\"333333\",\"profile_use_background_image\":true,\"profile_image_url\":\"http:\\/\\/pbs.twimg.com\\/profile_images\\/1327710858009571328\\/nXS2QXsf_normal.jpg\",\"profile_image_url_https\":\"https:\\/\\/pbs.twimg.com\\/profile_images\\/1327710858009571328\\/nXS2QXsf_normal.jpg\",\"profile_banner_url\":\"https:\\/\\/pbs.twimg.com\\/profile_banners\\/1327710660478820356\\/1605387287\",\"default_profile\":true,\"default_profile_image\":false,\"following\":null,\"follow_request_sent\":null,\"notifications\":null},\"geo\":null,\"coordinates\":null,\"place\":null,\"contributors\":null,\"quoted_status_id\":1336468604003307525,\"quoted_status_id_str\":\"1336468604003307525\",\"quoted_status\":{\"created_at\":\"Wed Dec 09 00:32:00 +0000 2020\",\"id\":1336468604003307525,\"id_str\":\"1336468604003307525\",\"text\":\"Do you use an iPhone? Watch Netflix? Listen to Spotify? Then you love capitalism and can't stand big government.\",\"source\":\"\\u003ca href=\\\"https:\\/\\/about.twitter.com\\/products\\/tweetdeck\\\" rel=\\\"nofollow\\\"\\u003eTweetDeck\\u003c\\/a\\u003e\",\"truncated\":false,\"in_reply_to_status_id\":null,\"in_reply_to_status_id_str\":null,\"in_reply_to_user_id\":null,\"in_reply_to_user_id_str\":null,\"in_reply_to_screen_name\":null,\"user\":{\"id\":41160276,\"id_str\":\"41160276\",\"name\":\"PragerU\",\"screen_name\":\"prageru\",\"location\":\"Los Angeles\",\"url\":\"http:\\/\\/www.prageru.com\",\"description\":\"Free Videos. Free Minds.\",\"translator_type\":\"none\",\"protected\":false,\"verified\":true,\"followers_count\":576856,\"friends_count\":6291,\"listed_count\":2430,\"favourites_count\":13889,\"statuses_count\":49598,\"created_at\":\"Tue May 19 17:18:19 +0000 2009\",\"utc_offset\":null,\"time_zone\":null,\"geo_enabled\":false,\"lang\":null,\"contributors_enabled\":false,\"is_translator\":false,\"profile_background_color\":\"FFFFFF\",\"profile_background_image_url\":\"http:\\/\\/abs.twimg.com\\/images\\/themes\\/theme1\\/bg.png\",\"profile_background_image_url_https\":\"https:\\/\\/abs.twimg.com\\/images\\/themes\\/theme1\\/bg.png\",\"profile_background_tile\":false,\"profile_link_color\":\"1B95E0\",\"profile_sidebar_border_color\":\"FFFFFF\",\"profile_sidebar_fill_color\":\"FFFFF5\",\"profile_text_color\":\"0C3E53\",\"profile_use_background_image\":true,\"profile_image_url\":\"http:\\/\\/pbs.twimg.com\\/profile_images\\/1188862949986725888\\/x7HIruKT_normal.jpg\",\"profile_image_url_https\":\"https:\\/\\/pbs.twimg.com\\/profile_images\\/1188862949986725888\\/x7HIruKT_normal.jpg\",\"profile_banner_url\":\"https:\\/\\/pbs.twimg.com\\/profile_banners\\/41160276\\/1579650070\",\"default_profile\":false,\"default_profile_image\":false,\"following\":null,\"follow_request_sent\":null,\"notifications\":null},\"geo\":null,\"coordinates\":null,\"place\":null,\"contributors\":null,\"is_quote_status\":false,\"quote_count\":896,\"reply_count\":1428,\"retweet_count\":354,\"favorite_count\":2952,\"entities\":{\"hashtags\":[],\"urls\":[],\"user_mentions\":[],\"symbols\":[]},\"favorited\":false,\"retweeted\":false,\"filter_level\":\"low\",\"lang\":\"en\"},\"quoted_status_permalink\":{\"url\":\"https:\\/\\/t.co\\/oSxD6Q7ER9\",\"expanded\":\"https:\\/\\/twitter.com\\/prageru\\/status\\/1336468604003307525\",\"display\":\"twitter.com\\/prageru\\/status\\u2026\"},\"is_quote_status\":true,\"extended_tweet\":{\"full_text\":\"Do you love the scraps of food you get from an abusive partner? Then you love your partner and wouldn't leave them for something better.\",\"display_text_range\":[0,136],\"entities\":{\"hashtags\":[],\"urls\":[],\"user_mentions\":[],\"symbols\":[]}},\"quote_count\":0,\"reply_count\":0,\"retweet_count\":0,\"favorite_count\":0,\"entities\":{\"hashtags\":[],\"urls\":[{\"url\":\"https:\\/\\/t.co\\/ckYD7t99zo\",\"expanded_url\":\"https:\\/\\/twitter.com\\/i\\/web\\/status\\/1336585736758419459\",\"display_url\":\"twitter.com\\/i\\/web\\/status\\/1\\u2026\",\"indices\":[116,139]}],\"user_mentions\":[],\"symbols\":[]},\"favorited\":false,\"retweeted\":false,\"filter_level\":\"low\",\"lang\":\"en\",\"timestamp_ms\":\"1607501846862\"}\r\n","test_col":1}
